ShengchengDuikangWangluoXiangmuChuyi/README.md
ShengchengDuikangWangluoXiangmuChuyi/__init__.py
ShengchengDuikangWangluoXiangmuChuyi/__main__.py
ShengchengDuikangWangluoXiangmuChuyi/file.epub
ShengchengDuikangWangluoXiangmuChuyi/index.html
ShengchengDuikangWangluoXiangmuChuyi/css/__init__.py
ShengchengDuikangWangluoXiangmuChuyi/css/annotations.css
ShengchengDuikangWangluoXiangmuChuyi/css/main.css
ShengchengDuikangWangluoXiangmuChuyi/css/normalize.css
ShengchengDuikangWangluoXiangmuChuyi/css/popup.css
ShengchengDuikangWangluoXiangmuChuyi/font/__init__.py
ShengchengDuikangWangluoXiangmuChuyi/font/fontello.eot
ShengchengDuikangWangluoXiangmuChuyi/font/fontello.svg
ShengchengDuikangWangluoXiangmuChuyi/font/fontello.ttf
ShengchengDuikangWangluoXiangmuChuyi/font/fontello.woff
ShengchengDuikangWangluoXiangmuChuyi/img/__init__.py
ShengchengDuikangWangluoXiangmuChuyi/img/annotator-glyph-sprite.png
ShengchengDuikangWangluoXiangmuChuyi/img/annotator-icon-sprite.png
ShengchengDuikangWangluoXiangmuChuyi/img/apple-touch-icon.png
ShengchengDuikangWangluoXiangmuChuyi/img/cancelfullscreen.png
ShengchengDuikangWangluoXiangmuChuyi/img/close.png
ShengchengDuikangWangluoXiangmuChuyi/img/fullscreen.png
ShengchengDuikangWangluoXiangmuChuyi/img/loader.gif
ShengchengDuikangWangluoXiangmuChuyi/img/menu-icon.png
ShengchengDuikangWangluoXiangmuChuyi/img/save.png
ShengchengDuikangWangluoXiangmuChuyi/img/saved.png
ShengchengDuikangWangluoXiangmuChuyi/img/settings-s.png
ShengchengDuikangWangluoXiangmuChuyi/img/settings.png
ShengchengDuikangWangluoXiangmuChuyi/img/star.png
ShengchengDuikangWangluoXiangmuChuyi/js/__init__.py
ShengchengDuikangWangluoXiangmuChuyi/js/epub.js
ShengchengDuikangWangluoXiangmuChuyi/js/epub.min.js
ShengchengDuikangWangluoXiangmuChuyi/js/epub.min.map
ShengchengDuikangWangluoXiangmuChuyi/js/hooks.min.js
ShengchengDuikangWangluoXiangmuChuyi/js/hooks.min.map
ShengchengDuikangWangluoXiangmuChuyi/js/reader.js
ShengchengDuikangWangluoXiangmuChuyi/js/reader.js.map
shengcheng_duikang_wangluo_xiangmu_chuyi-2024.3.5.0.dist-info/METADATA
shengcheng_duikang_wangluo_xiangmu_chuyi-2024.3.5.0.dist-info/WHEEL
shengcheng_duikang_wangluo_xiangmu_chuyi-2024.3.5.0.dist-info/entry_points.txt
shengcheng_duikang_wangluo_xiangmu_chuyi-2024.3.5.0.dist-info/top_level.txt
shengcheng_duikang_wangluo_xiangmu_chuyi-2024.3.5.0.dist-info/RECORD
